sample_vvs14/__init__.py
sample_vvs14/tests/__init__.py
sample_vvs14-0.0.1.dist-info/METADATA
sample_vvs14-0.0.1.dist-info/WHEEL
sample_vvs14-0.0.1.dist-info/top_level.txt
sample_vvs14-0.0.1.dist-info/RECORD
